MANIFEST.in
README.md
setup.py
messenger_bus/README.md
messenger_bus/__init__.py
messenger_bus/bus.py
messenger_bus/envelope.py
messenger_bus/exceptions.py
messenger_bus/message_handler.py
messenger_bus/middleware.py
messenger_bus/schema.yml
messenger_bus/serializer.py
messenger_bus/service_container.py
messenger_bus/stamp.py
messenger_bus/transport.py
messenger_bus/worker.py
messenger_bus.egg-info/PKG-INFO
messenger_bus.egg-info/SOURCES.txt
messenger_bus.egg-info/dependency_links.txt
messenger_bus.egg-info/requires.txt
messenger_bus.egg-info/top_level.txt
tests/test_command_interface.py