Metadata-Version: 2.1
Name: messenger-bus
Version: 1.0.27
Summary: Bus messaging system
Home-page: https://github.com/CoteOuestAudiovisuel/messenger_bus
Author: Zacharie Assagou
Author-email: zacharie.assagou@coteouest.ci
License: BSD 2-clause
